nxsugarpy/__init__.py
nxsugarpy/config.py
nxsugarpy/errors.py
nxsugarpy/helpers.py
nxsugarpy/info.py
nxsugarpy/log.py
nxsugarpy/server.py
nxsugarpy/service.py
nxsugarpy/signal.py
nxsugarpy/stats.py
nxsugarpy-1.3.14.dist-info/DESCRIPTION.rst
nxsugarpy-1.3.14.dist-info/METADATA
nxsugarpy-1.3.14.dist-info/RECORD
nxsugarpy-1.3.14.dist-info/WHEEL
nxsugarpy-1.3.14.dist-info/metadata.json
nxsugarpy-1.3.14.dist-info/top_level.txt
