Metadata-Version: 2.0
Name: nxsugarpy
Version: 1.3.14
Summary: Build microservices over Nexus
Home-page: https://github.com/nayarsystems/nxsugar-py
Author: Javier Sancho
Author-email: jsancho@nayarsystems.com
License: LGPLv3+
Keywords: nexus distributed microservices
Platform: UNKNOWN
Classifier: Development Status :: 4 - Beta
Classifier: Intended Audience :: Developers
Classifier: Topic :: Software Development :: Libraries :: Python Modules
Classifier: License :: OSI Approved :: GNU Lesser General Public License v3 or later (LGPLv3+)
Classifier: Programming Language :: Python :: 2.6
Classifier: Programming Language :: Python :: 2.7
Classifier: Programming Language :: Python :: 3
Classifier: Programming Language :: Python :: 3.2
Classifier: Programming Language :: Python :: 3.3
Classifier: Programming Language :: Python :: 3.4
Classifier: Programming Language :: Python :: 3.5
Requires-Dist: pynexus
Requires-Dist: strict-rfc3339
